README.md
setup.cfg
setup.py
ggwp/__init__.py
ggwp/test_run.py
ggwp.egg-info/PKG-INFO
ggwp.egg-info/SOURCES.txt
ggwp.egg-info/dependency_links.txt
ggwp.egg-info/requires.txt
ggwp.egg-info/top_level.txt
ggwp/EzDataModel/BasketEvolving.py
ggwp/EzDataModel/Cohort.py
ggwp/EzDataModel/CustomerMovement.py
ggwp/EzDataModel/DataModel.py
ggwp/EzDataModel/RFMT.py
ggwp/EzDataModel/__init__.py
ggwp/EzModeling/BenchMark.py
ggwp/EzModeling/Check.py
ggwp/EzModeling/Evaluation.py
ggwp/EzModeling/Log.py
ggwp/EzModeling/__init__.py
ggwp/EzPipeline/ColumnAssignment.py
ggwp/EzPipeline/ConvertVariables.py
ggwp/EzPipeline/DataFrameTransformer.py
ggwp/EzPipeline/GroupImputer.py
ggwp/EzPipeline/OneHotTransformer.py
ggwp/EzPipeline/__init__.py
ggwp/EzUtils/EzUtils.py
ggwp/EzUtils/__init__.py
ggwp/EzUtils/test_run.py
ggwp/config/__init__.py
ggwp/config/config.cfg
ggwp/config/config.py