Metadata-Version: 2.1
Name: ggwp
Version: 0.0.49
Summary: Prepare Fast, Analyze Faster
Home-page: https://github.com/datanooblol/ggwp
Author: Pathompol Nilchaikovit
Author-email: data.noob.lol@gmail.com
License: MIT
Platform: UNKNOWN
Classifier: Programming Language :: Python :: 3
Classifier: License :: OSI Approved :: MIT License
Classifier: Operating System :: OS Independent
Requires-Python: >=3.5
